{
  "month": "2026-04",
  "records": [
    {
      "employee_id": "vy",
      "late_count": 0,
      "late_penalty_each": 5,
      "overtime_days": 0,
      "days_off": 0,
      "bonus_amount": 0,
      "bonus_note": "",
      "sales_total": 0,
      "withholding": 0,
      "kiotviet_image": "",
      "calculated": {
        "overtime_total": 0.0,
        "late_total": 0,
        "days_off_deduction": 0.0,
        "commission": 0.0,
        "extra_bonus": 0,
        "total_salary": 5600.0
      }
    },
    {
      "employee_id": "an",
      "late_count": 0,
      "late_penalty_each": 5,
      "overtime_days": 21,
      "days_off": 7,
      "bonus_amount": 334,
      "bonus_note": "Gio to + 30/4 = 167*2",
      "sales_total": 11132,
      "withholding": 0,
      "kiotviet_image": "",
      "calculated": {
        "overtime_total": 388.5,
        "late_total": 0,
        "days_off_deduction": 1165.5,
        "commission": 222.6,
        "extra_bonus": 0,
        "total_salary": 5779.6
      }
    }
  ]
}